{
  "name": "tsparticles-interaction-light",
  "version": "1.37.0",
  "description": "tsParticles Light interaction",
  "homepage": "https://particles.js.org/",
  "repository": {
    "type": "git",
    "url": "git+https://github.com/matteobruni/tsparticles.git",
    "directory": "interactions/light"
  },
  "keywords": [
    "tsparticles",
    "particles",
    "particle",
    "canvas",
    "jsparticles",
    "xparticles",
    "particles-js",
    "particles.js",
    "particles-ts",
    "particles.ts",
    "typescript",
    "javascript",
    "animation",
    "web",
    "html5",
    "web-design",
    "webdesign",
    "css",
    "html",
    "css3",
    "animated",
    "background",
    "tsparticles-shape"
  ],
  "author": "Matteo Bruni",
  "license": "MIT",
  "bugs": {
    "url": "https://github.com/matteobruni/tsparticles/issues"
  },
  "main": "index.js",
  "jsdelivr": "tsparticles.interaction.light.min.js",
  "unpkg": "tsparticles.interaction.light.min.js",
  "browser": "index.js",
  "module": "index.js",
  "types": "index.d.ts",
  "dependencies": {
    "tsparticles": "^1.37.0"
  }
}